{
  "best_metric": null,
  "best_model_checkpoint": null,
  "epoch": 14.982456140350877,
  "global_step": 420,
  "is_hyper_param_search": false,
  "is_local_process_zero": true,
  "is_world_process_zero": true,
  "log_history": [
    {
      "epoch": 14.98,
      "step": 420,
      "total_flos": 1806305704798104.0,
      "train_loss": 0.4164559137253534,
      "train_runtime": 360.2628,
      "train_samples_per_second": 37.473,
      "train_steps_per_second": 1.166
    }
  ],
  "max_steps": 420,
  "num_train_epochs": 15,
  "total_flos": 1806305704798104.0,
  "trial_name": null,
  "trial_params": null
}
